yxspkg/Crawl_data.py
yxspkg/Gantt.py
yxspkg/SciencePlots.py
yxspkg/StockDataAPI.py
yxspkg/__init__.py
yxspkg/auto_move.py
yxspkg/auto_ups.py
yxspkg/cgns.py
yxspkg/command_line.py
yxspkg/convert_url.py
yxspkg/encrypt.py
yxspkg/fafa_excel.py
yxspkg/fig2ndarry.py
yxspkg/ftp_server.py
yxspkg/func2.py
yxspkg/get_history.py
yxspkg/get_input_ui.py
yxspkg/h5dataset.py
yxspkg/init_system.py
yxspkg/loop_cmd.py
yxspkg/m3u8.py
yxspkg/matplotlib_chinese.py
yxspkg/md5.py
yxspkg/message_client.py
yxspkg/message_server.py
yxspkg/mount_by_id.py
yxspkg/numeca_file.py
yxspkg/plot3d.py
yxspkg/proxy.py
yxspkg/pytecio.py
yxspkg/same_file.py
yxspkg/scfd_io.py
yxspkg/sci_plot.py
yxspkg/sleep_disk.py
yxspkg/songziviewer.py
yxspkg/sql.py
yxspkg/tecfile.py
yxspkg/tempCodeRunnerFile.py
yxspkg/tickets.py
yxspkg/video2html.py
yxspkg/wait_login.py
yxspkg/wallpaper.py
yxspkg/wget.py
yxspkg/xemail.py
yxspkg/xget.py
yxspkg/yxsfile.py
yxspkg/bin_file/simsun.ttc
yxspkg/deepin/__init__.py
yxspkg/deepin/kwin_replace.py
yxspkg/dog_cat/__init__.py
yxspkg/dog_cat/dog_cat.py
yxspkg/dog_cat/net.py
yxspkg/file_server/__init__.py
yxspkg/file_server/fe.py
yxspkg/file_server/flask_server.py
yxspkg/file_server/htmls.py
yxspkg/file_server/m_file.py
yxspkg/file_server/server.py
yxspkg/file_server/web_server.py
yxspkg/getdata/SourceImages.py
yxspkg/getdata/__init__.py
yxspkg/getdata/getdata.py
yxspkg/getdata/getdata_qt.py
yxspkg/html_lib/__init__.py
yxspkg/html_lib/_kube_css.py
yxspkg/html_lib/_style_css.py
yxspkg/html_lib/jquery_min_js.py
yxspkg/image/__init__.py
yxspkg/image/image_operator.py
yxspkg/lib_file/2017r2_tecio_so.py
yxspkg/lib_file/2017r3_tecio_dll.py
yxspkg/lib_file/__init__.py
yxspkg/lib_file/bin2017r2_tecio_so.py
yxspkg/lib_file/bin2017r3_tecio_dll.py
yxspkg/songzgif/CutImageWidget.py
yxspkg/songzgif/__init__.py
yxspkg/songzgif/gif.py
yxspkg/video/__init__.py
yxspkg/video/video_operator.py
yxspkg-6.19.8.dist-info/METADATA
yxspkg-6.19.8.dist-info/WHEEL
yxspkg-6.19.8.dist-info/entry_points.txt
yxspkg-6.19.8.dist-info/top_level.txt
yxspkg-6.19.8.dist-info/RECORD
