Metadata-Version: 2.1
Name: yxspkg
Version: 6.19.8
Summary: My pypi module
Home-page: https://github.com/blacksong
Author: Blacksong
Author-email: blacksong@yeah.net
Platform: python 3
Classifier: Programming Language :: Python :: 3
Classifier: Operating System :: OS Independent
Classifier: Topic :: Software Development :: Libraries :: Python Modules
